{
  "id": "5714c1ca-82c3-497d-a0fc-172985318601",
  "prevId": "00000000-0000-0000-0000-000000000000",
  "version": "7",
  "dialect": "postgresql",
  "tables": {
    "public.cv_data": {
      "name": "cv_data",
      "schema": "",
      "columns": {
        "id": {
          "name": "id",
          "type": "uuid",
          "primaryKey": true,
          "notNull": true,
          "default": "gen_random_uuid()"
        },
        "user_id": {
          "name": "user_id",
          "type": "text",
          "primaryKey": false,
          "notNull": true
        },
        "full_text": {
          "name": "full_text",
          "type": "text",
          "primaryKey": false,
          "notNull": true
        },
        "skills": {
          "name": "skills",
          "type": "jsonb",
          "primaryKey": false,
          "notNull": false
        },
        "experience": {
          "name": "experience",
          "type": "jsonb",
          "primaryKey": false,
          "notNull": false
        },
        "education": {
          "name": "education",
          "type": "jsonb",
          "primaryKey": false,
          "notNull": false
        },
        "certifications": {
          "name": "certifications",
          "type": "jsonb",
          "primaryKey": false,
          "notNull": false
        },
        "keywords": {
          "name": "keywords",
          "type": "text[]",
          "primaryKey": false,
          "notNull": false
        },
        "parsed_at": {
          "name": "parsed_at",
          "type": "timestamp",
          "primaryKey": false,
          "notNull": false,
          "default": "now()"
        },
        "updated_at": {
          "name": "updated_at",
          "type": "timestamp",
          "primaryKey": false,
          "notNull": false,
          "default": "now()"
        }
      },
      "indexes": {},
      "foreignKeys": {},
      "compositePrimaryKeys": {},
      "uniqueConstraints": {
        "cv_data_user_id_unique": {
          "name": "cv_data_user_id_unique",
          "nullsNotDistinct": false,
          "columns": [
            "user_id"
          ]
        }
      },
      "policies": {},
      "checkConstraints": {},
      "isRLSEnabled": false
    },
    "public.jobs": {
      "name": "jobs",
      "schema": "",
      "columns": {
        "id": {
          "name": "id",
          "type": "uuid",
          "primaryKey": true,
          "notNull": true,
          "default": "gen_random_uuid()"
        },
        "title": {
          "name": "title",
          "type": "text",
          "primaryKey": false,
          "notNull": true
        },
        "company": {
          "name": "company",
          "type": "text",
          "primaryKey": false,
          "notNull": true
        },
        "description": {
          "name": "description",
          "type": "text",
          "primaryKey": false,
          "notNull": false
        },
        "requirements": {
          "name": "requirements",
          "type": "text",
          "primaryKey": false,
          "notNull": false
        },
        "location": {
          "name": "location",
          "type": "text",
          "primaryKey": false,
          "notNull": false
        },
        "job_type": {
          "name": "job_type",
          "type": "text",
          "primaryKey": false,
          "notNull": false
        },
        "salary_min": {
          "name": "salary_min",
          "type": "integer",
          "primaryKey": false,
          "notNull": false
        },
        "salary_max": {
          "name": "salary_max",
          "type": "integer",
          "primaryKey": false,
          "notNull": false
        },
        "currency": {
          "name": "currency",
          "type": "text",
          "primaryKey": false,
          "notNull": false,
          "default": "'IDR'"
        },
        "link": {
          "name": "link",
          "type": "text",
          "primaryKey": false,
          "notNull": true
        },
        "source": {
          "name": "source",
          "type": "text",
          "primaryKey": false,
          "notNull": true
        },
        "scraped_at": {
          "name": "scraped_at",
          "type": "timestamp",
          "primaryKey": false,
          "notNull": false,
          "default": "now()"
        },
        "posted_at": {
          "name": "posted_at",
          "type": "timestamp",
          "primaryKey": false,
          "notNull": false
        },
        "created_at": {
          "name": "created_at",
          "type": "timestamp",
          "primaryKey": false,
          "notNull": false,
          "default": "now()"
        },
        "updated_at": {
          "name": "updated_at",
          "type": "timestamp",
          "primaryKey": false,
          "notNull": false,
          "default": "now()"
        }
      },
      "indexes": {},
      "foreignKeys": {},
      "compositePrimaryKeys": {},
      "uniqueConstraints": {
        "unique_link_source": {
          "name": "unique_link_source",
          "nullsNotDistinct": false,
          "columns": [
            "link",
            "source"
          ]
        }
      },
      "policies": {},
      "checkConstraints": {},
      "isRLSEnabled": false
    },
    "public.matches": {
      "name": "matches",
      "schema": "",
      "columns": {
        "id": {
          "name": "id",
          "type": "uuid",
          "primaryKey": true,
          "notNull": true,
          "default": "gen_random_uuid()"
        },
        "job_id": {
          "name": "job_id",
          "type": "uuid",
          "primaryKey": false,
          "notNull": true
        },
        "cv_id": {
          "name": "cv_id",
          "type": "uuid",
          "primaryKey": false,
          "notNull": true
        },
        "match_score": {
          "name": "match_score",
          "type": "integer",
          "primaryKey": false,
          "notNull": false
        },
        "skills_match": {
          "name": "skills_match",
          "type": "integer",
          "primaryKey": false,
          "notNull": false
        },
        "experience_match": {
          "name": "experience_match",
          "type": "integer",
          "primaryKey": false,
          "notNull": false
        },
        "keywords_match": {
          "name": "keywords_match",
          "type": "integer",
          "primaryKey": false,
          "notNull": false
        },
        "breakdown": {
          "name": "breakdown",
          "type": "jsonb",
          "primaryKey": false,
          "notNull": false
        },
        "created_at": {
          "name": "created_at",
          "type": "timestamp",
          "primaryKey": false,
          "notNull": false,
          "default": "now()"
        }
      },
      "indexes": {},
      "foreignKeys": {
        "matches_job_id_jobs_id_fk": {
          "name": "matches_job_id_jobs_id_fk",
          "tableFrom": "matches",
          "tableTo": "jobs",
          "columnsFrom": [
            "job_id"
          ],
          "columnsTo": [
            "id"
          ],
          "onDelete": "no action",
          "onUpdate": "no action"
        },
        "matches_cv_id_cv_data_id_fk": {
          "name": "matches_cv_id_cv_data_id_fk",
          "tableFrom": "matches",
          "tableTo": "cv_data",
          "columnsFrom": [
            "cv_id"
          ],
          "columnsTo": [
            "id"
          ],
          "onDelete": "no action",
          "onUpdate": "no action"
        }
      },
      "compositePrimaryKeys": {},
      "uniqueConstraints": {
        "unique_job_cv": {
          "name": "unique_job_cv",
          "nullsNotDistinct": false,
          "columns": [
            "job_id",
            "cv_id"
          ]
        }
      },
      "policies": {},
      "checkConstraints": {},
      "isRLSEnabled": false
    }
  },
  "enums": {},
  "schemas": {},
  "sequences": {},
  "roles": {},
  "policies": {},
  "views": {},
  "_meta": {
    "columns": {},
    "schemas": {},
    "tables": {}
  }
}